setup.py
pouch/__init__.py
pouch.egg-info/PKG-INFO
pouch.egg-info/SOURCES.txt
pouch.egg-info/dependency_links.txt
pouch.egg-info/requires.txt
pouch.egg-info/top_level.txt
test/test_models.py