Metadata-Version: 1.0
Name: pouch
Version: 0.1.0
Summary: Python library for interfacing with couchdb
Home-page: http://code.google.com/p/pouch/
Author: Mikeal Rogers
Author-email: mikeal.rogers@gmail.com
License: Python license
Platform: Any
Classifier: Development Status :: 4 - Beta
Classifier: Environment :: Console
Classifier: Intended Audience :: Developers
Classifier: License :: OSI Approved :: Apache Software License
Classifier: Operating System :: OS Independent
Classifier: Topic :: Software Development :: Libraries :: Python Modules
